sigma/backends/crowdstrike/__init__.py
sigma/backends/crowdstrike/logscale.py
sigma/pipelines/crowdstrike/__init__.py
sigma/pipelines/crowdstrike/crowdstrike.py
pysigma_backend_crowdstrike-2.0.1.dist-info/LICENSE
pysigma_backend_crowdstrike-2.0.1.dist-info/METADATA
pysigma_backend_crowdstrike-2.0.1.dist-info/WHEEL
pysigma_backend_crowdstrike-2.0.1.dist-info/RECORD
