Metadata-Version: 2.1
Name: pysigma-backend-crowdstrike
Version: 2.0.1
Summary: pySigma CrowdStrike Logscale backend and processing pipelines for the Falcon data model.
Home-page: https://github.com/SigmaHQ/pySigma-backend-crowdstrike
License: LGPL-2.1-only
Author: Panos Moullotos
Requires-Python: >=3.8,<4.0
Classifier: License :: OSI Approved
Classifier: Programming Language :: Python :: 3
Classifier: Programming Language :: Python :: 3.8
Classifier: Programming Language :: Python :: 3.9
Classifier: Programming Language :: Python :: 3.10
Classifier: Programming Language :: Python :: 3.11
Classifier: Programming Language :: Python :: 3.12
Requires-Dist: pysigma (>=0.11.13,<0.12.0)
Project-URL: Repository, https://github.com/SigmaHQ/pySigma-backend-crowdstrike
